[
    {
        "href":"http://hd.mall.meizu.com/yuyue/meizunote9.html",
        "img":"https://fms.res.meizu.com/dms/2019/03/01/f45fb529-2484-40b5-ae50-d0dbdf9971c8.jpg"
    },
    {
        "href":"https://detail.meizu.com/item/meizux8.html?click=store_index_dh_1_4&click=click_store_index_dh_1_4",
        "img":"https://fms.res.meizu.com/dms/2019/02/18/e03b8b38-8826-4351-9a51-c3a91a07c5f7.jpg"
    },
    {
        "href":"https://detail.meizu.com/item/meizu_ep51.html",
        "img":"https://fms.res.meizu.com/dms/2018/12/20/ae34c0ad-0a55-4357-9ca0-4a57a59b55b4.jpg"
    }
]